pypitesty/__init__.py
pypitesty/foo.py
pypitesty/bar/__init__.py
pypitesty/bar/baz.py
pypitesty-1.2.0.dist-info/DESCRIPTION.rst
pypitesty-1.2.0.dist-info/METADATA
pypitesty-1.2.0.dist-info/RECORD
pypitesty-1.2.0.dist-info/WHEEL
pypitesty-1.2.0.dist-info/metadata.json
pypitesty-1.2.0.dist-info/top_level.txt
