Metadata-Version: 2.0
Name: pypitesty
Version: 1.2.0
Summary: python connection tools collection
Home-page: UNKNOWN
Author: luoanni
Author-email: luoanni33@gmail.com
License: Copyright (c) 2016, James Liu
Requires-Dist: qPython (>=2.0.0)
